README.md
setup.py
upstash_pulumi/__init__.py
upstash_pulumi/_utilities.py
upstash_pulumi/get_q_stash_endpoint.py
upstash_pulumi/get_q_stash_schedule.py
upstash_pulumi/get_q_stash_schedule_v2.py
upstash_pulumi/get_q_stash_topic.py
upstash_pulumi/get_q_stash_topic_v2.py
upstash_pulumi/get_redis_database.py
upstash_pulumi/get_search.py
upstash_pulumi/get_team.py
upstash_pulumi/get_vector_index.py
upstash_pulumi/get_vector_index_v2.py
upstash_pulumi/provider.py
upstash_pulumi/pulumi-plugin.json
upstash_pulumi/py.typed
upstash_pulumi/q_stash_endpoint.py
upstash_pulumi/q_stash_schedule.py
upstash_pulumi/q_stash_schedule_v2.py
upstash_pulumi/q_stash_topic.py
upstash_pulumi/q_stash_topic_v2.py
upstash_pulumi/redis_database.py
upstash_pulumi/search.py
upstash_pulumi/team.py
upstash_pulumi/vector_index.py
upstash_pulumi.egg-info/PKG-INFO
upstash_pulumi.egg-info/SOURCES.txt
upstash_pulumi.egg-info/dependency_links.txt
upstash_pulumi.egg-info/not-zip-safe
upstash_pulumi.egg-info/requires.txt
upstash_pulumi.egg-info/top_level.txt
upstash_pulumi/config/__init__.py
upstash_pulumi/config/vars.py