Metadata-Version: 2.1
Name: upstash-pulumi
Version: 0.5.0
Summary: A Pulumi package for creating and managing upstash cloud resources.
Home-page: https://www.upstash.com
License: Apache-2.0
Project-URL: Repository, https://github.com/upstash/pulumi-upstash
Keywords: pulumi upstash category/cloud
Platform: UNKNOWN
Requires-Python: >=3.9
